[{"id": "e-0-8434", "size": 5, "cages": [{"cells": [{"r": 0, "c": 0}], "target": 5, "op": "="}, {"cells": [{"r": 3, "c": 3}, {"r": 3, "c": 4}], "target": 8, "op": "+"}, {"cells": [{"r": 2, "c": 4}, {"r": 2, "c": 3}], "target": 5, "op": "+"}, {"cells": [{"r": 1, "c": 3}, {"r": 1, "c": 2}], "target": 7, "op": "+"}, {"cells": [{"r": 2, "c": 1}, {"r": 2, "c": 0}], "target": 8, "op": "+"}, {"cells": [{"r": 4, "c": 0}, {"r": 3, "c": 0}], "target": 6, "op": "+"}, {"cells": [{"r": 2, "c": 2}, {"r": 3, "c": 2}], "target": 6, "op": "+"}, {"cells": [{"r": 4, "c": 4}, {"r": 4, "c": 3}], "target": 6, "op": "+"}, {"cells": [{"r": 1, "c": 1}, {"r": 0, "c": 1}], "target": 7, "op": "+"}, {"cells": [{"r": 0, "c": 2}, {"r": 0, "c": 3}], "target": 5, "op": "+"}, {"cells": [{"r": 0, "c": 4}, {"r": 1, "c": 4}], "target": 5, "op": "+"}, {"cells": [{"r": 4, "c": 2}, {"r": 4, "c": 1}], "target": 5, "op": "+"}, {"cells": [{"r": 1, "c": 0}], "target": 1, "op": "="}, {"cells": [{"r": 3, "c": 1}], "target": 1, "op": "="}], "solution": [[5, 3, 1, 4, 2], [1, 4, 5, 2, 3], [3, 5, 2, 1, 4], [2, 1, 4, 3, 5], [4, 2, 3, 5, 1]]}, {"id": "e-0-4335", "size": 5, "cages": [{"cells": [{"r": 1, "c": 0}], "target": 5, "op": "="}, {"cells": [{"r": 0, "c": 3}, {"r": 1, "c": 3}], "target": 5, "op": "+"}, {"cells": [{"r": 4, "c": 1}, {"r": 4, "c": 0}], "target": 7, "op": "+"}, {"cells": [{"r": 1, "c": 2}, {"r": 1, "c": 1}], "target": 3, "op": "+"}, {"cells": [{"r": 0, "c": 2}, {"r": 0, "c": 1}], "target": 4, "op": "+"}, {"cells": [{"r": 2, "c": 0}, {"r": 2, "c": 1}], "target": 7, "op": "+"}, {"cells": [{"r": 4, "c": 4}, {"r": 3, "c": 4}], "target": 4, "op": "+"}, {"cells": [{"r": 0, "c": 4}, {"r": 1, "c": 4}], "target": 9, "op": "+"}, {"cells": [{"r": 3, "c": 0}, {"r": 3, "c": 1}], "target": 3, "op": "+"}, {"cells": [{"r": 0, "c": 0}], "target": 4, "op": "="}, {"cells": [{"r": 3, "c": 2}, {"r": 4, "c": 2}], "target": 7, "op": "+"}, {"cells": [{"r": 4, "c": 3}, {"r": 3, "c": 3}], "target": 9, "op": "+"}, {"cells": [{"r": 2, "c": 3}, {"r": 2, "c": 4}], "target": 3, "op": "+"}, {"cells": [{"r": 2, "c": 2}], "target": 5, "op": "="}], "solution": [[4, 3, 1, 2, 5], [5, 1, 2, 3, 4], [3, 4, 5, 1, 2], [1, 2, 4, 5, 3], [2, 5, 3, 4, 1]]}, {"id": "e-0-2476", "size": 5, "cages": [{"cells": [{"r": 0, "c": 3}], "target": 3, "op": "="}, {"cells": [{"r": 4, "c": 4}, {"r": 4, "c": 3}], "target": 3, "op": "+"}, {"cells": [{"r": 3, "c": 0}, {"r": 4, "c": 0}], "target": 7, "op": "+"}, {"cells": [{"r": 4, "c": 2}, {"r": 4, "c": 1}], "target": 8, "op": "+"}, {"cells": [{"r": 2, "c": 2}, {"r": 2, "c": 3}], "target": 6, "op": "+"}, {"cells": [{"r": 3, "c": 2}, {"r": 3, "c": 3}], "target": 7, "op": "+"}, {"cells": [{"r": 3, "c": 4}, {"r": 2, "c": 4}], "target": 4, "op": "+"}, {"cells": [{"r": 3, "c": 1}, {"r": 2, "c": 1}], "target": 5, "op": "+"}, {"cells": [{"r": 1, "c": 2}, {"r": 1, "c": 3}], "target": 5, "op": "+"}, {"cells": [{"r": 1, "c": 1}, {"r": 0, "c": 1}], "target": 5, "op": "+"}, {"cells": [{"r": 2, "c": 0}, {"r": 1, "c": 0}], "target": 7, "op": "+"}, {"cells": [{"r": 0, "c": 2}], "target": 5, "op": "="}, {"cells": [{"r": 0, "c": 0}], "target": 1, "op": "="}, {"cells": [{"r": 0, "c": 4}, {"r": 1, "c": 4}], "target": 9, "op": "+"}], "solution": [[1, 2, 5, 3, 4], [2, 3, 1, 4, 5], [5, 1, 4, 2, 3], [3, 4, 2, 5, 1], [4, 5, 3, 1, 2]]}, {"id": "e-1-8245", "size": 5, "cages": [{"cells": [{"r": 2, "c": 1}], "target": 4, "op": "="}, {"cells": [{"r": 4, "c": 1}, {"r": 4, "c": 0}], "target": 6, "op": "+"}, {"cells": [{"r": 3, "c": 3}, {"r": 4, "c": 3}], "target": 7, "op": "+"}, {"cells": [{"r": 1, "c": 2}, {"r": 0, "c": 2}], "target": 6, "op": "+"}, {"cells": [{"r": 1, "c": 4}, {"r": 1, "c": 3}], "target": 4, "op": "+"}, {"cells": [{"r": 0, "c": 1}, {"r": 0, "c": 0}], "target": 5, "op": "+"}, {"cells": [{"r": 0, "c": 3}, {"r": 0, "c": 4}], "target": 6, "op": "+"}, {"cells": [{"r": 3, "c": 1}, {"r": 3, "c": 2}], "target": 7, "op": "+"}, {"cells": [{"r": 4, "c": 2}], "target": 3, "op": "="}, {"cells": [{"r": 1, "c": 0}, {"r": 2, "c": 0}], "target": 7, "op": "+"}, {"cells": [{"r": 2, "c": 3}, {"r": 2, "c": 4}], "target": 7, "op": "+"}, {"cells": [{"r": 1, "c": 1}], "target": 5, "op": "="}, {"cells": [{"r": 3, "c": 0}], "target": 1, "op": "="}, {"cells": [{"r": 3, "c": 4}, {"r": 4, "c": 4}], "target": 6, "op": "+"}, {"cells": [{"r": 2, "c": 2}], "target": 1, "op": "="}], "solution": [[2, 3, 4, 5, 1], [4, 5, 2, 1, 3], [3, 4, 1, 2, 5], [1, 2, 5, 3, 4], [5, 1, 3, 4, 2]]}, {"id": "e-0-1461", "size": 5, "cages": [{"cells": [{"r": 0, "c": 0}], "target": 2, "op": "="}, {"cells": [{"r": 0, "c": 4}, {"r": 0, "c": 3}], "target": 6, "op": "+"}, {"cells": [{"r": 4, "c": 1}, {"r": 3, "c": 1}], "target": 6, "op": "+"}, {"cells": [{"r": 1, "c": 3}, {"r": 1, "c": 2}], "target": 6, "op": "+"}, {"cells": [{"r": 3, "c": 4}, {"r": 4, "c": 4}], "target": 6, "op": "+"}, {"cells": [{"r": 2, "c": 2}, {"r": 2, "c": 1}], "target": 7, "op": "+"}, {"cells": [{"r": 4, "c": 3}, {"r": 4, "c": 2}], "target": 7, "op": "+"}, {"cells": [{"r": 3, "c": 2}, {"r": 3, "c": 3}], "target": 3, "op": "+"}, {"cells": [{"r": 0, "c": 2}, {"r": 0, "c": 1}], "target": 7, "op": "+"}, {"cells": [{"r": 2, "c": 0}, {"r": 3, "c": 0}], "target": 7, "op": "+"}, {"cells": [{"r": 4, "c": 0}], "target": 5, "op": "="}, {"cells": [{"r": 2, "c": 3}, {"r": 2, "c": 4}], "target": 4, "op": "+"}, {"cells": [{"r": 1, "c": 1}, {"r": 1, "c": 0}], "target": 4, "op": "+"}, {"cells": [{"r": 1, "c": 4}], "target": 5, "op": "="}], "solution": [[2, 4, 3, 5, 1], [1, 3, 2, 4, 5], [4, 2, 5, 1, 3], [3, 5, 1, 2, 4], [5, 1, 4, 3, 2]]}, {"id": "e-4-9777", "size": 5, "cages": [{"cells": [{"r": 3, "c": 0}], "target": 4, "op": "="}, {"cells": [{"r": 4, "c": 2}, {"r": 4, "c": 3}], "target": 6, "op": "+"}, {"cells": [{"r": 1, "c": 4}, {"r": 2, "c": 4}], "target": 5, "op": "+"}, {"cells": [{"r": 1, "c": 0}, {"r": 0, "c": 0}], "target": 3, "op": "+"}, {"cells": [{"r": 2, "c": 2}, {"r": 3, "c": 2}], "target": 9, "op": "+"}, {"cells": [{"r": 3, "c": 4}, {"r": 4, "c": 4}], "target": 5, "op": "+"}, {"cells": [{"r": 2, "c": 3}, {"r": 1, "c": 3}], "target": 7, "op": "+"}, {"cells": [{"r": 0, "c": 4}, {"r": 0, "c": 3}], "target": 6, "op": "+"}, {"cells": [{"r": 3, "c": 1}, {"r": 2, "c": 1}], "target": 4, "op": "+"}, {"cells": [{"r": 0, "c": 1}, {"r": 0, "c": 2}], "target": 7, "op": "+"}, {"cells": [{"r": 4, "c": 0}, {"r": 4, "c": 1}], "target": 5, "op": "+"}, {"cells": [{"r": 3, "c": 3}], "target": 2, "op": "="}, {"cells": [{"r": 2, "c": 0}], "target": 5, "op": "="}, {"cells": [{"r": 1, "c": 2}, {"r": 1, "c": 1}], "target": 7, "op": "+"}], "solution": [[2, 4, 3, 1, 5], [1, 5, 2, 4, 3], [5, 1, 4, 3, 2], [4, 3, 5, 2, 1], [3, 2, 1, 5, 4]]}, {"id": "e-1-5873", "size": 5, "cages": [{"cells": [{"r": 1, "c": 1}], "target": 5, "op": "="}, {"cells": [{"r": 2, "c": 4}, {"r": 1, "c": 4}], "target": 8, "op": "+"}, {"cells": [{"r": 2, "c": 0}, {"r": 3, "c": 0}], "target": 5, "op": "+"}, {"cells": [{"r": 4, "c": 0}, {"r": 4, "c": 1}], "target": 6, "op": "+"}, {"cells": [{"r": 3, "c": 2}, {"r": 2, "c": 2}], "target": 3, "op": "+"}, {"cells": [{"r": 4, "c": 2}, {"r": 4, "c": 3}], "target": 8, "op": "+"}, {"cells": [{"r": 0, "c": 3}, {"r": 0, "c": 4}], "target": 6, "op": "+"}, {"cells": [{"r": 3, "c": 1}, {"r": 2, "c": 1}], "target": 7, "op": "+"}, {"cells": [{"r": 0, "c": 1}, {"r": 0, "c": 2}], "target": 4, "op": "+"}, {"cells": [{"r": 1, "c": 0}, {"r": 0, "c": 0}], "target": 6, "op": "+"}, {"cells": [{"r": 4, "c": 4}, {"r": 3, "c": 4}], "target": 5, "op": "+"}, {"cells": [{"r": 2, "c": 3}, {"r": 3, "c": 3}], "target": 6, "op": "+"}, {"cells": [{"r": 1, "c": 2}, {"r": 1, "c": 3}], "target": 6, "op": "+"}], "solution": [[5, 1, 3, 4, 2], [1, 5, 4, 2, 3], [3, 4, 2, 1, 5], [2, 3, 1, 5, 4], [4, 2, 5, 3, 1]]}, {"id": "e-2-8570", "size": 5, "cages": [{"cells": [{"r": 3, "c": 2}], "target": 5, "op": "="}, {"cells": [{"r": 2, "c": 2}, {"r": 2, "c": 1}], "target": 4, "op": "+"}, {"cells": [{"r": 0, "c": 1}, {"r": 1, "c": 1}], "target": 5, "op": "+"}, {"cells": [{"r": 2, "c": 0}, {"r": 1, "c": 0}], "target": 7, "op": "+"}, {"cells": [{"r": 0, "c": 0}], "target": 5, "op": "="}, {"cells": [{"r": 0, "c": 3}, {"r": 1, "c": 3}], "target": 9, "op": "+"}, {"cells": [{"r": 3, "c": 4}, {"r": 3, "c": 3}], "target": 4, "op": "+"}, {"cells": [{"r": 4, "c": 2}, {"r": 4, "c": 1}], "target": 9, "op": "+"}, {"cells": [{"r": 2, "c": 4}, {"r": 1, "c": 4}], "target": 9, "op": "+"}, {"cells": [{"r": 0, "c": 2}, {"r": 1, "c": 2}], "target": 3, "op": "+"}, {"cells": [{"r": 0, "c": 4}], "target": 1, "op": "="}, {"cells": [{"r": 2, "c": 3}], "target": 2, "op": "="}, {"cells": [{"r": 3, "c": 1}, {"r": 3, "c": 0}], "target": 6, "op": "+"}, {"cells": [{"r": 4, "c": 3}, {"r": 4, "c": 4}], "target": 5, "op": "+"}, {"cells": [{"r": 4, "c": 0}], "target": 1, "op": "="}], "solution": [[5, 3, 2, 4, 1], [3, 2, 1, 5, 4], [4, 1, 3, 2, 5], [2, 4, 5, 1, 3], [1, 5, 4, 3, 2]]}, {"id": "e-1-1613", "size": 5, "cages": [{"cells": [{"r": 1, "c": 0}], "target": 3, "op": "="}, {"cells": [{"r": 0, "c": 2}, {"r": 0, "c": 1}], "target": 7, "op": "+"}, {"cells": [{"r": 4, "c": 3}, {"r": 3, "c": 3}], "target": 5, "op": "+"}, {"cells": [{"r": 1, "c": 3}, {"r": 1, "c": 2}], "target": 7, "op": "+"}, {"cells": [{"r": 3, "c": 1}, {"r": 3, "c": 2}], "target": 4, "op": "+"}, {"cells": [{"r": 0, "c": 3}, {"r": 0, "c": 4}], "target": 4, "op": "+"}, {"cells": [{"r": 4, "c": 4}, {"r": 3, "c": 4}], "target": 6, "op": "+"}, {"cells": [{"r": 2, "c": 3}, {"r": 2, "c": 2}], "target": 5, "op": "+"}, {"cells": [{"r": 0, "c": 0}], "target": 4, "op": "="}, {"cells": [{"r": 3, "c": 0}, {"r": 2, "c": 0}], "target": 7, "op": "+"}, {"cells": [{"r": 4, "c": 1}, {"r": 4, "c": 2}], "target": 9, "op": "+"}, {"cells": [{"r": 1, "c": 4}, {"r": 2, "c": 4}], "target": 6, "op": "+"}, {"cells": [{"r": 2, "c": 1}, {"r": 1, "c": 1}], "target": 7, "op": "+"}, {"cells": [{"r": 4, "c": 0}], "target": 1, "op": "="}], "solution": [[4, 2, 5, 1, 3], [3, 4, 2, 5, 1], [2, 3, 1, 4, 5], [5, 1, 3, 2, 4], [1, 5, 4, 3, 2]]}, {"id": "e-0-7889", "size": 5, "cages": [{"cells": [{"r": 0, "c": 2}], "target": 5, "op": "="}, {"cells": [{"r": 2, "c": 0}, {"r": 2, "c": 1}], "target": 9, "op": "+"}, {"cells": [{"r": 2, "c": 2}, {"r": 2, "c": 3}], "target": 4, "op": "+"}, {"cells": [{"r": 4, "c": 4}, {"r": 4, "c": 3}], "target": 8, "op": "+"}, {"cells": [{"r": 4, "c": 1}, {"r": 4, "c": 0}], "target": 3, "op": "+"}, {"cells": [{"r": 3, "c": 1}, {"r": 3, "c": 2}], "target": 6, "op": "+"}, {"cells": [{"r": 1, "c": 1}, {"r": 1, "c": 2}], "target": 3, "op": "+"}, {"cells": [{"r": 0, "c": 4}, {"r": 0, "c": 3}], "target": 3, "op": "+"}, {"cells": [{"r": 0, "c": 0}, {"r": 1, "c": 0}], "target": 7, "op": "+"}, {"cells": [{"r": 4, "c": 2}], "target": 4, "op": "="}, {"cells": [{"r": 3, "c": 4}, {"r": 2, "c": 4}], "target": 5, "op": "+"}, {"cells": [{"r": 3, "c": 3}], "target": 4, "op": "="}, {"cells": [{"r": 0, "c": 1}], "target": 3, "op": "="}, {"cells": [{"r": 1, "c": 3}, {"r": 1, "c": 4}], "target": 9, "op": "+"}, {"cells": [{"r": 3, "c": 0}], "target": 2, "op": "="}], "solution": [[4, 3, 5, 2, 1], [3, 1, 2, 5, 4], [5, 4, 3, 1, 2], [2, 5, 1, 4, 3], [1, 2, 4, 3, 5]]}, {"id": "e-0-2635", "size": 5, "cages": [{"cells": [{"r": 2, "c": 1}], "target": 1, "op": "="}, {"cells": [{"r": 3, "c": 1}, {"r": 4, "c": 1}], "target": 9, "op": "+"}, {"cells": [{"r": 2, "c": 0}, {"r": 3, "c": 0}], "target": 6, "op": "+"}, {"cells": [{"r": 1, "c": 1}, {"r": 1, "c": 0}], "target": 5, "op": "+"}, {"cells": [{"r": 4, "c": 4}, {"r": 3, "c": 4}], "target": 4, "op": "+"}, {"cells": [{"r": 4, "c": 3}, {"r": 3, "c": 3}], "target": 7, "op": "+"}, {"cells": [{"r": 0, "c": 3}, {"r": 0, "c": 2}], "target": 6, "op": "+"}, {"cells": [{"r": 4, "c": 2}, {"r": 3, "c": 2}], "target": 3, "op": "+"}, {"cells": [{"r": 2, "c": 2}, {"r": 2, "c": 3}], "target": 8, "op": "+"}, {"cells": [{"r": 0, "c": 1}, {"r": 0, "c": 0}], "target": 4, "op": "+"}, {"cells": [{"r": 1, "c": 4}, {"r": 2, "c": 4}], "target": 6, "op": "+"}, {"cells": [{"r": 1, "c": 3}, {"r": 1, "c": 2}], "target": 6, "op": "+"}, {"cells": [{"r": 0, "c": 4}], "target": 5, "op": "="}, {"cells": [{"r": 4, "c": 0}], "target": 5, "op": "="}], "solution": [[1, 3, 4, 2, 5], [3, 2, 5, 1, 4], [4, 1, 3, 5, 2], [2, 5, 1, 4, 3], [5, 4, 2, 3, 1]]}, {"id": "e-1-2572", "size": 5, "cages": [{"cells": [{"r": 0, "c": 0}], "target": 1, "op": "="}, {"cells": [{"r": 4, "c": 3}, {"r": 3, "c": 3}], "target": 5, "op": "+"}, {"cells": [{"r": 1, "c": 3}, {"r": 1, "c": 2}], "target": 5, "op": "+"}, {"cells": [{"r": 2, "c": 1}, {"r": 3, "c": 1}], "target": 7, "op": "+"}, {"cells": [{"r": 1, "c": 4}, {"r": 0, "c": 4}], "target": 7, "op": "+"}, {"cells": [{"r": 2, "c": 2}, {"r": 2, "c": 3}], "target": 3, "op": "+"}, {"cells": [{"r": 1, "c": 0}, {"r": 2, "c": 0}], "target": 7, "op": "+"}, {"cells": [{"r": 1, "c": 1}, {"r": 0, "c": 1}], "target": 4, "op": "+"}, {"cells": [{"r": 3, "c": 4}, {"r": 4, "c": 4}], "target": 4, "op": "+"}, {"cells": [{"r": 2, "c": 4}], "target": 4, "op": "="}, {"cells": [{"r": 3, "c": 2}, {"r": 4, "c": 2}], "target": 8, "op": "+"}, {"cells": [{"r": 4, "c": 1}, {"r": 4, "c": 0}], "target": 6, "op": "+"}, {"cells": [{"r": 0, "c": 3}, {"r": 0, "c": 2}], "target": 9, "op": "+"}, {"cells": [{"r": 3, "c": 0}], "target": 5, "op": "="}], "solution": [[1, 3, 4, 5, 2], [4, 1, 2, 3, 5], [3, 5, 1, 2, 4], [5, 2, 3, 4, 1], [2, 4, 5, 1, 3]]}, {"id": "e-0-4585", "size": 5, "cages": [{"cells": [{"r": 1, "c": 4}], "target": 5, "op": "="}, {"cells": [{"r": 4, "c": 2}, {"r": 4, "c": 3}], "target": 4, "op": "+"}, {"cells": [{"r": 3, "c": 1}, {"r": 2, "c": 1}], "target": 5, "op": "+"}, {"cells": [{"r": 2, "c": 0}, {"r": 1, "c": 0}], "target": 7, "op": "+"}, {"cells": [{"r": 3, "c": 4}, {"r": 3, "c": 3}], "target": 7, "op": "+"}, {"cells": [{"r": 2, "c": 3}, {"r": 2, "c": 2}], "target": 7, "op": "+"}, {"cells": [{"r": 1, "c": 2}, {"r": 1, "c": 3}], "target": 3, "op": "+"}, {"cells": [{"r": 0, "c": 3}, {"r": 0, "c": 2}], "target": 7, "op": "+"}, {"cells": [{"r": 4, "c": 4}], "target": 4, "op": "="}, {"cells": [{"r": 4, "c": 1}, {"r": 4, "c": 0}], "target": 7, "op": "+"}, {"cells": [{"r": 0, "c": 0}, {"r": 0, "c": 1}], "target": 6, "op": "+"}, {"cells": [{"r": 1, "c": 1}], "target": 4, "op": "="}, {"cells": [{"r": 3, "c": 2}], "target": 5, "op": "="}, {"cells": [{"r": 3, "c": 0}], "target": 1, "op": "="}, {"cells": [{"r": 0, "c": 4}], "target": 2, "op": "="}, {"cells": [{"r": 2, "c": 4}], "target": 1, "op": "="}], "solution": [[5, 1, 4, 3, 2], [3, 4, 1, 2, 5], [4, 3, 2, 5, 1], [1, 2, 5, 4, 3], [2, 5, 3, 1, 4]]}, {"id": "e-0-6990", "size": 5, "cages": [{"cells": [{"r": 3, "c": 2}], "target": 2, "op": "="}, {"cells": [{"r": 0, "c": 1}, {"r": 0, "c": 2}], "target": 5, "op": "+"}, {"cells": [{"r": 0, "c": 0}, {"r": 1, "c": 0}], "target": 4, "op": "+"}, {"cells": [{"r": 1, "c": 1}, {"r": 1, "c": 2}], "target": 7, "op": "+"}, {"cells": [{"r": 3, "c": 1}, {"r": 2, "c": 1}], "target": 4, "op": "+"}, {"cells": [{"r": 2, "c": 4}, {"r": 1, "c": 4}], "target": 5, "op": "+"}, {"cells": [{"r": 2, "c": 3}, {"r": 3, "c": 3}], "target": 8, "op": "+"}, {"cells": [{"r": 4, "c": 4}, {"r": 4, "c": 3}], "target": 5, "op": "+"}, {"cells": [{"r": 1, "c": 3}, {"r": 0, "c": 3}], "target": 6, "op": "+"}, {"cells": [{"r": 3, "c": 4}], "target": 1, "op": "="}, {"cells": [{"r": 3, "c": 0}, {"r": 4, "c": 0}], "target": 6, "op": "+"}, {"cells": [{"r": 4, "c": 1}, {"r": 4, "c": 2}], "target": 8, "op": "+"}, {"cells": [{"r": 2, "c": 2}], "target": 4, "op": "="}, {"cells": [{"r": 2, "c": 0}], "target": 5, "op": "="}, {"cells": [{"r": 0, "c": 4}], "target": 5, "op": "="}], "solution": [[3, 4, 1, 2, 5], [1, 2, 5, 4, 3], [5, 1, 4, 3, 2], [4, 3, 2, 5, 1], [2, 5, 3, 1, 4]]}, {"id": "e-0-6621", "size": 5, "cages": [{"cells": [{"r": 3, "c": 2}], "target": 1, "op": "="}, {"cells": [{"r": 2, "c": 1}, {"r": 2, "c": 0}], "target": 6, "op": "+"}, {"cells": [{"r": 4, "c": 1}, {"r": 4, "c": 0}], "target": 4, "op": "+"}, {"cells": [{"r": 1, "c": 0}, {"r": 1, "c": 1}], "target": 9, "op": "+"}, {"cells": [{"r": 3, "c": 0}, {"r": 3, "c": 1}], "target": 5, "op": "+"}, {"cells": [{"r": 0, "c": 3}, {"r": 0, "c": 4}], "target": 5, "op": "+"}, {"cells": [{"r": 3, "c": 4}, {"r": 4, "c": 4}], "target": 6, "op": "+"}, {"cells": [{"r": 1, "c": 4}, {"r": 1, "c": 3}], "target": 4, "op": "+"}, {"cells": [{"r": 0, "c": 2}, {"r": 0, "c": 1}], "target": 9, "op": "+"}, {"cells": [{"r": 4, "c": 3}, {"r": 3, "c": 3}], "target": 9, "op": "+"}, {"cells": [{"r": 1, "c": 2}, {"r": 2, "c": 2}], "target": 5, "op": "+"}, {"cells": [{"r": 0, "c": 0}], "target": 1, "op": "="}, {"cells": [{"r": 4, "c": 2}], "target": 5, "op": "="}, {"cells": [{"r": 2, "c": 4}, {"r": 2, "c": 3}], "target": 6, "op": "+"}], "solution": [[1, 5, 4, 2, 3], [5, 4, 2, 3, 1], [4, 2, 3, 1, 5], [2, 3, 1, 5, 4], [3, 1, 5, 4, 2]]}, {"id": "e-0-4788", "size": 5, "cages": [{"cells": [{"r": 4, "c": 4}], "target": 5, "op": "="}, {"cells": [{"r": 3, "c": 3}, {"r": 3, "c": 4}], "target": 5, "op": "+"}, {"cells": [{"r": 1, "c": 1}, {"r": 1, "c": 2}], "target": 4, "op": "+"}, {"cells": [{"r": 2, "c": 2}, {"r": 2, "c": 3}], "target": 9, "op": "+"}, {"cells": [{"r": 0, "c": 0}, {"r": 0, "c": 1}], "target": 6, "op": "+"}, {"cells": [{"r": 3, "c": 2}, {"r": 4, "c": 2}], "target": 8, "op": "+"}, {"cells": [{"r": 2, "c": 0}, {"r": 3, "c": 0}], "target": 7, "op": "+"}, {"cells": [{"r": 1, "c": 0}], "target": 5, "op": "="}, {"cells": [{"r": 0, "c": 4}, {"r": 1, "c": 4}], "target": 7, "op": "+"}, {"cells": [{"r": 1, "c": 3}, {"r": 0, "c": 3}], "target": 6, "op": "+"}, {"cells": [{"r": 2, "c": 4}], "target": 1, "op": "="}, {"cells": [{"r": 3, "c": 1}, {"r": 4, "c": 1}], "target": 5, "op": "+"}, {"cells": [{"r": 4, "c": 0}], "target": 2, "op": "="}, {"cells": [{"r": 0, "c": 2}], "target": 2, "op": "="}, {"cells": [{"r": 4, "c": 3}], "target": 1, "op": "="}, {"cells": [{"r": 2, "c": 1}], "target": 2, "op": "="}], "solution": [[1, 5, 2, 4, 3], [5, 3, 1, 2, 4], [3, 2, 4, 5, 1], [4, 1, 5, 3, 2], [2, 4, 3, 1, 5]]}, {"id": "e-1-8076", "size": 5, "cages": [{"cells": [{"r": 0, "c": 3}], "target": 4, "op": "="}, {"cells": [{"r": 4, "c": 4}, {"r": 3, "c": 4}], "target": 7, "op": "+"}, {"cells": [{"r": 3, "c": 1}, {"r": 3, "c": 2}], "target": 4, "op": "+"}, {"cells": [{"r": 1, "c": 3}, {"r": 1, "c": 4}], "target": 4, "op": "+"}, {"cells": [{"r": 2, "c": 2}, {"r": 1, "c": 2}], "target": 8, "op": "+"}, {"cells": [{"r": 0, "c": 0}, {"r": 1, "c": 0}], "target": 7, "op": "+"}, {"cells": [{"r": 2, "c": 0}, {"r": 2, "c": 1}], "target": 9, "op": "+"}, {"cells": [{"r": 0, "c": 1}, {"r": 1, "c": 1}], "target": 3, "op": "+"}, {"cells": [{"r": 4, "c": 2}, {"r": 4, "c": 3}], "target": 6, "op": "+"}, {"cells": [{"r": 4, "c": 0}, {"r": 3, "c": 0}], "target": 3, "op": "+"}, {"cells": [{"r": 2, "c": 4}, {"r": 2, "c": 3}], "target": 3, "op": "+"}, {"cells": [{"r": 3, "c": 3}], "target": 5, "op": "="}, {"cells": [{"r": 0, "c": 2}], "target": 2, "op": "="}, {"cells": [{"r": 4, "c": 1}], "target": 5, "op": "="}, {"cells": [{"r": 0, "c": 4}], "target": 5, "op": "="}], "solution": [[3, 1, 2, 4, 5], [4, 2, 5, 3, 1], [5, 4, 3, 1, 2], [2, 3, 1, 5, 4], [1, 5, 4, 2, 3]]}, {"id": "e-2-9558", "size": 5, "cages": [{"cells": [{"r": 1, "c": 2}], "target": 5, "op": "="}, {"cells": [{"r": 2, "c": 2}, {"r": 2, "c": 1}], "target": 5, "op": "+"}, {"cells": [{"r": 0, "c": 1}, {"r": 0, "c": 0}], "target": 6, "op": "+"}, {"cells": [{"r": 4, "c": 1}, {"r": 4, "c": 0}], "target": 9, "op": "+"}, {"cells": [{"r": 3, "c": 0}, {"r": 3, "c": 1}], "target": 8, "op": "+"}, {"cells": [{"r": 3, "c": 2}, {"r": 3, "c": 3}], "target": 3, "op": "+"}, {"cells": [{"r": 0, "c": 2}, {"r": 0, "c": 3}], "target": 8, "op": "+"}, {"cells": [{"r": 3, "c": 4}, {"r": 2, "c": 4}], "target": 9, "op": "+"}, {"cells": [{"r": 2, "c": 0}, {"r": 1, "c": 0}], "target": 4, "op": "+"}, {"cells": [{"r": 4, "c": 2}, {"r": 4, "c": 3}], "target": 4, "op": "+"}, {"cells": [{"r": 1, "c": 1}], "target": 2, "op": "="}, {"cells": [{"r": 4, "c": 4}], "target": 2, "op": "="}, {"cells": [{"r": 1, "c": 3}, {"r": 2, "c": 3}], "target": 6, "op": "+"}, {"cells": [{"r": 0, "c": 4}, {"r": 1, "c": 4}], "target": 4, "op": "+"}], "solution": [[2, 4, 3, 5, 1], [1, 2, 5, 4, 3], [3, 1, 4, 2, 5], [5, 3, 2, 1, 4], [4, 5, 1, 3, 2]]}, {"id": "e-1-6653", "size": 5, "cages": [{"cells": [{"r": 0, "c": 3}], "target": 3, "op": "="}, {"cells": [{"r": 4, "c": 3}, {"r": 4, "c": 4}], "target": 5, "op": "+"}, {"cells": [{"r": 3, "c": 1}, {"r": 3, "c": 0}], "target": 5, "op": "+"}, {"cells": [{"r": 1, "c": 0}, {"r": 2, "c": 0}], "target": 6, "op": "+"}, {"cells": [{"r": 2, "c": 4}, {"r": 2, "c": 3}], "target": 3, "op": "+"}, {"cells": [{"r": 2, "c": 2}, {"r": 2, "c": 1}], "target": 8, "op": "+"}, {"cells": [{"r": 0, "c": 0}, {"r": 0, "c": 1}], "target": 5, "op": "+"}, {"cells": [{"r": 3, "c": 3}, {"r": 3, "c": 4}], "target": 9, "op": "+"}, {"cells": [{"r": 4, "c": 2}, {"r": 3, "c": 2}], "target": 3, "op": "+"}, {"cells": [{"r": 4, "c": 0}, {"r": 4, "c": 1}], "target": 8, "op": "+"}, {"cells": [{"r": 1, "c": 3}, {"r": 1, "c": 4}], "target": 8, "op": "+"}, {"cells": [{"r": 1, "c": 1}, {"r": 1, "c": 2}], "target": 5, "op": "+"}, {"cells": [{"r": 0, "c": 4}], "target": 2, "op": "="}, {"cells": [{"r": 0, "c": 2}], "target": 5, "op": "="}], "solution": [[1, 4, 5, 3, 2], [2, 1, 4, 5, 3], [4, 5, 3, 2, 1], [3, 2, 1, 4, 5], [5, 3, 2, 1, 4]]}, {"id": "e-0-9748", "size": 5, "cages": [{"cells": [{"r": 4, "c": 4}], "target": 3, "op": "="}, {"cells": [{"r": 3, "c": 3}, {"r": 3, "c": 4}], "target": 3, "op": "+"}, {"cells": [{"r": 4, "c": 3}, {"r": 4, "c": 2}], "target": 3, "op": "+"}, {"cells": [{"r": 2, "c": 0}, {"r": 1, "c": 0}], "target": 5, "op": "+"}, {"cells": [{"r": 1, "c": 1}, {"r": 1, "c": 2}], "target": 5, "op": "+"}, {"cells": [{"r": 0, "c": 1}, {"r": 0, "c": 0}], "target": 3, "op": "+"}, {"cells": [{"r": 2, "c": 4}, {"r": 2, "c": 3}], "target": 6, "op": "+"}, {"cells": [{"r": 1, "c": 4}, {"r": 0, "c": 4}], "target": 9, "op": "+"}, {"cells": [{"r": 3, "c": 0}, {"r": 4, "c": 0}], "target": 8, "op": "+"}, {"cells": [{"r": 0, "c": 3}, {"r": 1, "c": 3}], "target": 7, "op": "+"}, {"cells": [{"r": 3, "c": 1}, {"r": 2, "c": 1}], "target": 7, "op": "+"}, {"cells": [{"r": 2, "c": 2}, {"r": 3, "c": 2}], "target": 7, "op": "+"}, {"cells": [{"r": 0, "c": 2}], "target": 5, "op": "="}, {"cells": [{"r": 4, "c": 1}], "target": 4, "op": "="}], "solution": [[2, 1, 5, 3, 4], [1, 3, 2, 4, 5], [4, 2, 3, 5, 1], [3, 5, 4, 1, 2], [5, 4, 1, 2, 3]]}, {"id": "e-0-2820", "size": 5, "cages": [{"cells": [{"r": 0, "c": 4}], "target": 1, "op": "="}, {"cells": [{"r": 2, "c": 3}, {"r": 3, "c": 3}], "target": 8, "op": "+"}, {"cells": [{"r": 3, "c": 1}, {"r": 4, "c": 1}], "target": 4, "op": "+"}, {"cells": [{"r": 0, "c": 2}, {"r": 0, "c": 3}], "target": 9, "op": "+"}, {"cells": [{"r": 4, "c": 4}, {"r": 4, "c": 3}], "target": 7, "op": "+"}, {"cells": [{"r": 0, "c": 1}, {"r": 0, "c": 0}], "target": 5, "op": "+"}, {"cells": [{"r": 2, "c": 1}, {"r": 1, "c": 1}], "target": 9, "op": "+"}, {"cells": [{"r": 3, "c": 0}, {"r": 2, "c": 0}], "target": 6, "op": "+"}, {"cells": [{"r": 1, "c": 4}, {"r": 2, "c": 4}], "target": 5, "op": "+"}, {"cells": [{"r": 1, "c": 2}, {"r": 2, "c": 2}], "target": 3, "op": "+"}, {"cells": [{"r": 1, "c": 3}], "target": 1, "op": "="}, {"cells": [{"r": 1, "c": 0}], "target": 5, "op": "="}, {"cells": [{"r": 3, "c": 4}], "target": 4, "op": "="}, {"cells": [{"r": 4, "c": 0}], "target": 1, "op": "="}, {"cells": [{"r": 4, "c": 2}, {"r": 3, "c": 2}], "target": 7, "op": "+"}], "solution": [[3, 2, 5, 4, 1], [5, 4, 2, 1, 3], [4, 5, 1, 3, 2], [2, 1, 3, 5, 4], [1, 3, 4, 2, 5]]}, {"id": "e-0-6021", "size": 5, "cages": [{"cells": [{"r": 4, "c": 3}], "target": 5, "op": "="}, {"cells": [{"r": 3, "c": 3}, {"r": 2, "c": 3}], "target": 5, "op": "+"}, {"cells": [{"r": 1, "c": 0}, {"r": 0, "c": 0}], "target": 5, "op": "+"}, {"cells": [{"r": 2, "c": 2}, {"r": 1, "c": 2}], "target": 3, "op": "+"}, {"cells": [{"r": 3, "c": 0}, {"r": 4, "c": 0}], "target": 5, "op": "+"}, {"cells": [{"r": 0, "c": 3}, {"r": 0, "c": 2}], "target": 6, "op": "+"}, {"cells": [{"r": 2, "c": 4}, {"r": 3, "c": 4}], "target": 7, "op": "+"}, {"cells": [{"r": 1, "c": 4}, {"r": 1, "c": 3}], "target": 8, "op": "+"}, {"cells": [{"r": 0, "c": 4}], "target": 1, "op": "="}, {"cells": [{"r": 3, "c": 1}, {"r": 3, "c": 2}], "target": 7, "op": "+"}, {"cells": [{"r": 1, "c": 1}, {"r": 2, "c": 1}], "target": 7, "op": "+"}, {"cells": [{"r": 2, "c": 0}], "target": 5, "op": "="}, {"cells": [{"r": 4, "c": 1}, {"r": 4, "c": 2}], "target": 4, "op": "+"}, {"cells": [{"r": 4, "c": 4}], "target": 2, "op": "="}, {"cells": [{"r": 0, "c": 1}], "target": 5, "op": "="}], "solution": [[3, 5, 4, 2, 1], [2, 4, 1, 3, 5], [5, 3, 2, 1, 4], [1, 2, 5, 4, 3], [4, 1, 3, 5, 2]]}, {"id": "e-0-5225", "size": 5, "cages": [{"cells": [{"r": 4, "c": 4}], "target": 4, "op": "="}, {"cells": [{"r": 1, "c": 4}, {"r": 0, "c": 4}], "target": 7, "op": "+"}, {"cells": [{"r": 2, "c": 2}, {"r": 2, "c": 1}], "target": 7, "op": "+"}, {"cells": [{"r": 0, "c": 3}, {"r": 1, "c": 3}], "target": 8, "op": "+"}, {"cells": [{"r": 0, "c": 1}, {"r": 0, "c": 0}], "target": 6, "op": "+"}, {"cells": [{"r": 2, "c": 0}, {"r": 1, "c": 0}], "target": 4, "op": "+"}, {"cells": [{"r": 1, "c": 1}, {"r": 1, "c": 2}], "target": 5, "op": "+"}, {"cells": [{"r": 0, "c": 2}], "target": 1, "op": "="}, {"cells": [{"r": 2, "c": 3}, {"r": 3, "c": 3}], "target": 6, "op": "+"}, {"cells": [{"r": 4, "c": 2}, {"r": 3, "c": 2}], "target": 8, "op": "+"}, {"cells": [{"r": 3, "c": 1}, {"r": 4, "c": 1}], "target": 7, "op": "+"}, {"cells": [{"r": 4, "c": 0}, {"r": 3, "c": 0}], "target": 7, "op": "+"}, {"cells": [{"r": 3, "c": 4}, {"r": 2, "c": 4}], "target": 4, "op": "+"}, {"cells": [{"r": 4, "c": 3}], "target": 1, "op": "="}], "solution": [[4, 2, 1, 3, 5], [3, 1, 4, 5, 2], [1, 5, 2, 4, 3], [5, 4, 3, 2, 1], [2, 3, 5, 1, 4]]}, {"id": "e-1-1364", "size": 5, "cages": [{"cells": [{"r": 0, "c": 1}], "target": 1, "op": "="}, {"cells": [{"r": 0, "c": 2}, {"r": 0, "c": 3}], "target": 7, "op": "+"}, {"cells": [{"r": 1, "c": 1}, {"r": 1, "c": 2}], "target": 7, "op": "+"}, {"cells": [{"r": 2, "c": 4}, {"r": 1, "c": 4}], "target": 9, "op": "+"}, {"cells": [{"r": 4, "c": 1}, {"r": 4, "c": 0}], "target": 6, "op": "+"}, {"cells": [{"r": 0, "c": 0}, {"r": 1, "c": 0}], "target": 8, "op": "+"}, {"cells": [{"r": 3, "c": 2}, {"r": 4, "c": 2}], "target": 6, "op": "+"}, {"cells": [{"r": 2, "c": 2}, {"r": 2, "c": 1}], "target": 6, "op": "+"}, {"cells": [{"r": 4, "c": 3}, {"r": 3, "c": 3}], "target": 7, "op": "+"}, {"cells": [{"r": 4, "c": 4}, {"r": 3, "c": 4}], "target": 4, "op": "+"}, {"cells": [{"r": 2, "c": 0}, {"r": 3, "c": 0}], "target": 5, "op": "+"}, {"cells": [{"r": 2, "c": 3}, {"r": 1, "c": 3}], "target": 4, "op": "+"}, {"cells": [{"r": 0, "c": 4}], "target": 2, "op": "="}, {"cells": [{"r": 3, "c": 1}], "target": 3, "op": "="}], "solution": [[5, 1, 3, 4, 2], [3, 5, 2, 1, 4], [1, 2, 4, 3, 5], [4, 3, 5, 2, 1], [2, 4, 1, 5, 3]]}, {"id": "e-0-8786", "size": 5, "cages": [{"cells": [{"r": 1, "c": 2}], "target": 5, "op": "="}, {"cells": [{"r": 1, "c": 3}, {"r": 1, "c": 4}], "target": 5, "op": "+"}, {"cells": [{"r": 4, "c": 4}, {"r": 4, "c": 3}], "target": 9, "op": "+"}, {"cells": [{"r": 0, "c": 0}, {"r": 1, "c": 0}], "target": 4, "op": "+"}, {"cells": [{"r": 0, "c": 2}, {"r": 0, "c": 3}], "target": 7, "op": "+"}, {"cells": [{"r": 4, "c": 1}, {"r": 4, "c": 0}], "target": 5, "op": "+"}, {"cells": [{"r": 4, "c": 2}, {"r": 3, "c": 2}], "target": 3, "op": "+"}, {"cells": [{"r": 2, "c": 2}, {"r": 2, "c": 3}], "target": 5, "op": "+"}, {"cells": [{"r": 2, "c": 1}, {"r": 3, "c": 1}], "target": 5, "op": "+"}, {"cells": [{"r": 3, "c": 4}, {"r": 3, "c": 3}], "target": 4, "op": "+"}, {"cells": [{"r": 2, "c": 0}, {"r": 3, "c": 0}], "target": 9, "op": "+"}, {"cells": [{"r": 1, "c": 1}, {"r": 0, "c": 1}], "target": 7, "op": "+"}, {"cells": [{"r": 0, "c": 4}], "target": 2, "op": "="}, {"cells": [{"r": 2, "c": 4}], "target": 5, "op": "="}], "solution": [[1, 5, 4, 3, 2], [3, 2, 5, 4, 1], [4, 1, 3, 2, 5], [5, 4, 2, 1, 3], [2, 3, 1, 5, 4]]}, {"id": "e-1-8825", "size": 5, "cages": [{"cells": [{"r": 2, "c": 4}], "target": 5, "op": "="}, {"cells": [{"r": 3, "c": 2}, {"r": 3, "c": 1}], "target": 7, "op": "+"}, {"cells": [{"r": 2, "c": 3}, {"r": 3, "c": 3}], "target": 7, "op": "+"}, {"cells": [{"r": 0, "c": 2}, {"r": 0, "c": 3}], "target": 6, "op": "+"}, {"cells": [{"r": 4, "c": 2}, {"r": 4, "c": 3}], "target": 6, "op": "+"}, {"cells": [{"r": 0, "c": 0}, {"r": 0, "c": 1}], "target": 6, "op": "+"}, {"cells": [{"r": 4, "c": 1}, {"r": 4, "c": 0}], "target": 5, "op": "+"}, {"cells": [{"r": 0, "c": 4}, {"r": 1, "c": 4}], "target": 5, "op": "+"}, {"cells": [{"r": 2, "c": 1}, {"r": 1, "c": 1}], "target": 8, "op": "+"}, {"cells": [{"r": 3, "c": 4}, {"r": 4, "c": 4}], "target": 5, "op": "+"}, {"cells": [{"r": 2, "c": 0}, {"r": 1, "c": 0}], "target": 5, "op": "+"}, {"cells": [{"r": 1, "c": 2}, {"r": 1, "c": 3}], "target": 7, "op": "+"}, {"cells": [{"r": 3, "c": 0}], "target": 2, "op": "="}, {"cells": [{"r": 2, "c": 2}], "target": 1, "op": "="}], "solution": [[5, 1, 2, 4, 3], [1, 5, 4, 3, 2], [4, 3, 1, 2, 5], [2, 4, 3, 5, 1], [3, 2, 5, 1, 4]]}, {"id": "e-1-8210", "size": 5, "cages": [{"cells": [{"r": 0, "c": 2}], "target": 3, "op": "="}, {"cells": [{"r": 2, "c": 1}, {"r": 3, "c": 1}], "target": 3, "op": "+"}, {"cells": [{"r": 0, "c": 3}, {"r": 0, "c": 4}], "target": 6, "op": "+"}, {"cells": [{"r": 0, "c": 1}, {"r": 1, "c": 1}], "target": 9, "op": "+"}, {"cells": [{"r": 4, "c": 1}, {"r": 4, "c": 0}], "target": 4, "op": "+"}, {"cells": [{"r": 3, "c": 2}, {"r": 4, "c": 2}], "target": 6, "op": "+"}, {"cells": [{"r": 2, "c": 4}, {"r": 1, "c": 4}], "target": 4, "op": "+"}, {"cells": [{"r": 2, "c": 3}, {"r": 3, "c": 3}], "target": 7, "op": "+"}, {"cells": [{"r": 4, "c": 3}, {"r": 4, "c": 4}], "target": 6, "op": "+"}, {"cells": [{"r": 0, "c": 0}, {"r": 1, "c": 0}], "target": 6, "op": "+"}, {"cells": [{"r": 2, "c": 2}, {"r": 1, "c": 2}], "target": 6, "op": "+"}, {"cells": [{"r": 3, "c": 0}, {"r": 2, "c": 0}], "target": 8, "op": "+"}, {"cells": [{"r": 1, "c": 3}], "target": 3, "op": "="}, {"cells": [{"r": 3, "c": 4}], "target": 4, "op": "="}], "solution": [[2, 4, 3, 1, 5], [4, 5, 2, 3, 1], [5, 1, 4, 2, 3], [3, 2, 1, 5, 4], [1, 3, 5, 4, 2]]}, {"id": "e-0-8932", "size": 5, "cages": [{"cells": [{"r": 2, "c": 4}], "target": 2, "op": "="}, {"cells": [{"r": 2, "c": 2}, {"r": 1, "c": 2}], "target": 4, "op": "+"}, {"cells": [{"r": 0, "c": 2}, {"r": 0, "c": 3}], "target": 8, "op": "+"}, {"cells": [{"r": 1, "c": 3}, {"r": 1, "c": 4}], "target": 7, "op": "+"}, {"cells": [{"r": 4, "c": 2}, {"r": 4, "c": 3}], "target": 9, "op": "+"}, {"cells": [{"r": 3, "c": 4}, {"r": 3, "c": 3}], "target": 7, "op": "+"}, {"cells": [{"r": 3, "c": 1}, {"r": 4, "c": 1}], "target": 7, "op": "+"}, {"cells": [{"r": 3, "c": 2}], "target": 2, "op": "="}, {"cells": [{"r": 0, "c": 4}], "target": 4, "op": "="}, {"cells": [{"r": 1, "c": 0}, {"r": 0, "c": 0}], "target": 6, "op": "+"}, {"cells": [{"r": 2, "c": 1}, {"r": 2, "c": 0}], "target": 9, "op": "+"}, {"cells": [{"r": 1, "c": 1}, {"r": 0, "c": 1}], "target": 4, "op": "+"}, {"cells": [{"r": 4, "c": 4}], "target": 1, "op": "="}, {"cells": [{"r": 3, "c": 0}, {"r": 4, "c": 0}], "target": 4, "op": "+"}, {"cells": [{"r": 2, "c": 3}], "target": 1, "op": "="}], "solution": [[2, 1, 5, 3, 4], [4, 3, 1, 2, 5], [5, 4, 3, 1, 2], [1, 5, 2, 4, 3], [3, 2, 4, 5, 1]]}, {"id": "e-0-2029", "size": 5, "cages": [{"cells": [{"r": 1, "c": 2}], "target": 3, "op": "="}, {"cells": [{"r": 4, "c": 0}, {"r": 3, "c": 0}], "target": 8, "op": "+"}, {"cells": [{"r": 2, "c": 4}, {"r": 3, "c": 4}], "target": 4, "op": "+"}, {"cells": [{"r": 0, "c": 1}, {"r": 0, "c": 2}], "target": 6, "op": "+"}, {"cells": [{"r": 1, "c": 4}, {"r": 1, "c": 3}], "target": 7, "op": "+"}, {"cells": [{"r": 0, "c": 0}, {"r": 1, "c": 0}], "target": 3, "op": "+"}, {"cells": [{"r": 4, "c": 3}, {"r": 4, "c": 2}], "target": 9, "op": "+"}, {"cells": [{"r": 1, "c": 1}, {"r": 2, "c": 1}], "target": 6, "op": "+"}, {"cells": [{"r": 3, "c": 1}, {"r": 4, "c": 1}], "target": 4, "op": "+"}, {"cells": [{"r": 0, "c": 3}, {"r": 0, "c": 4}], "target": 7, "op": "+"}, {"cells": [{"r": 2, "c": 3}, {"r": 2, "c": 2}], "target": 6, "op": "+"}, {"cells": [{"r": 3, "c": 3}, {"r": 3, "c": 2}], "target": 6, "op": "+"}, {"cells": [{"r": 4, "c": 4}], "target": 2, "op": "="}, {"cells": [{"r": 2, "c": 0}], "target": 4, "op": "="}], "solution": [[2, 5, 1, 3, 4], [1, 4, 3, 2, 5], [4, 2, 5, 1, 3], [5, 3, 2, 4, 1], [3, 1, 4, 5, 2]]}, {"id": "e-0-6368", "size": 5, "cages": [{"cells": [{"r": 2, "c": 2}], "target": 1, "op": "="}, {"cells": [{"r": 0, "c": 1}, {"r": 1, "c": 1}], "target": 8, "op": "+"}, {"cells": [{"r": 1, "c": 3}, {"r": 2, "c": 3}], "target": 6, "op": "+"}, {"cells": [{"r": 3, "c": 3}, {"r": 4, "c": 3}], "target": 7, "op": "+"}, {"cells": [{"r": 1, "c": 0}, {"r": 0, "c": 0}], "target": 6, "op": "+"}, {"cells": [{"r": 3, "c": 2}, {"r": 3, "c": 1}], "target": 3, "op": "+"}, {"cells": [{"r": 0, "c": 4}, {"r": 0, "c": 3}], "target": 3, "op": "+"}, {"cells": [{"r": 2, "c": 4}, {"r": 3, "c": 4}], "target": 7, "op": "+"}, {"cells": [{"r": 0, "c": 2}, {"r": 1, "c": 2}], "target": 7, "op": "+"}, {"cells": [{"r": 3, "c": 0}, {"r": 2, "c": 0}], "target": 8, "op": "+"}, {"cells": [{"r": 4, "c": 4}], "target": 2, "op": "="}, {"cells": [{"r": 2, "c": 1}], "target": 2, "op": "="}, {"cells": [{"r": 1, "c": 4}], "target": 5, "op": "="}, {"cells": [{"r": 4, "c": 0}, {"r": 4, "c": 1}], "target": 5, "op": "+"}, {"cells": [{"r": 4, "c": 2}], "target": 5, "op": "="}], "solution": [[4, 5, 3, 2, 1], [2, 3, 4, 1, 5], [3, 2, 1, 5, 4], [5, 1, 2, 4, 3], [1, 4, 5, 3, 2]]}, {"id": "e-2-6043", "size": 5, "cages": [{"cells": [{"r": 3, "c": 2}], "target": 2, "op": "="}, {"cells": [{"r": 4, "c": 0}, {"r": 4, "c": 1}], "target": 8, "op": "+"}, {"cells": [{"r": 3, "c": 1}, {"r": 2, "c": 1}], "target": 7, "op": "+"}, {"cells": [{"r": 2, "c": 0}, {"r": 3, "c": 0}], "target": 4, "op": "+"}, {"cells": [{"r": 4, "c": 4}, {"r": 4, "c": 3}], "target": 3, "op": "+"}, {"cells": [{"r": 1, "c": 4}, {"r": 2, "c": 4}], "target": 9, "op": "+"}, {"cells": [{"r": 1, "c": 2}, {"r": 0, "c": 2}], "target": 8, "op": "+"}, {"cells": [{"r": 3, "c": 3}, {"r": 3, "c": 4}], "target": 7, "op": "+"}, {"cells": [{"r": 4, "c": 2}], "target": 4, "op": "="}, {"cells": [{"r": 0, "c": 1}, {"r": 1, "c": 1}], "target": 5, "op": "+"}, {"cells": [{"r": 2, "c": 3}, {"r": 2, "c": 2}], "target": 6, "op": "+"}, {"cells": [{"r": 0, "c": 0}, {"r": 1, "c": 0}], "target": 6, "op": "+"}, {"cells": [{"r": 0, "c": 3}, {"r": 0, "c": 4}], "target": 4, "op": "+"}, {"cells": [{"r": 1, "c": 3}], "target": 2, "op": "="}], "solution": [[2, 4, 5, 3, 1], [4, 1, 3, 2, 5], [3, 2, 1, 5, 4], [1, 5, 2, 4, 3], [5, 3, 4, 1, 2]]}, {"id": "e-0-3625", "size": 5, "cages": [{"cells": [{"r": 3, "c": 3}], "target": 1, "op": "="}, {"cells": [{"r": 3, "c": 4}, {"r": 4, "c": 4}], "target": 5, "op": "+"}, {"cells": [{"r": 4, "c": 2}, {"r": 4, "c": 1}], "target": 4, "op": "+"}, {"cells": [{"r": 2, "c": 3}, {"r": 2, "c": 2}], "target": 5, "op": "+"}, {"cells": [{"r": 0, "c": 0}, {"r": 1, "c": 0}], "target": 8, "op": "+"}, {"cells": [{"r": 1, "c": 1}, {"r": 1, "c": 2}], "target": 7, "op": "+"}, {"cells": [{"r": 0, "c": 2}, {"r": 0, "c": 1}], "target": 3, "op": "+"}, {"cells": [{"r": 3, "c": 1}, {"r": 2, "c": 1}], "target": 9, "op": "+"}, {"cells": [{"r": 2, "c": 4}, {"r": 1, "c": 4}], "target": 5, "op": "+"}, {"cells": [{"r": 2, "c": 0}, {"r": 3, "c": 0}], "target": 3, "op": "+"}, {"cells": [{"r": 0, "c": 3}, {"r": 1, "c": 3}], "target": 6, "op": "+"}, {"cells": [{"r": 4, "c": 3}], "target": 5, "op": "="}, {"cells": [{"r": 3, "c": 2}], "target": 5, "op": "="}, {"cells": [{"r": 4, "c": 0}], "target": 4, "op": "="}, {"cells": [{"r": 0, "c": 4}], "target": 5, "op": "="}], "solution": [[3, 2, 1, 4, 5], [5, 3, 4, 2, 1], [1, 5, 2, 3, 4], [2, 4, 5, 1, 3], [4, 1, 3, 5, 2]]}, {"id": "e-2-5742", "size": 5, "cages": [{"cells": [{"r": 1, "c": 0}], "target": 4, "op": "="}, {"cells": [{"r": 3, "c": 1}, {"r": 3, "c": 0}], "target": 4, "op": "+"}, {"cells": [{"r": 3, "c": 4}, {"r": 4, "c": 4}], "target": 6, "op": "+"}, {"cells": [{"r": 4, "c": 1}, {"r": 4, "c": 0}], "target": 5, "op": "+"}, {"cells": [{"r": 3, "c": 3}, {"r": 4, "c": 3}], "target": 9, "op": "+"}, {"cells": [{"r": 2, "c": 1}, {"r": 2, "c": 0}], "target": 9, "op": "+"}, {"cells": [{"r": 0, "c": 4}, {"r": 1, "c": 4}], "target": 7, "op": "+"}, {"cells": [{"r": 2, "c": 4}, {"r": 2, "c": 3}], "target": 5, "op": "+"}, {"cells": [{"r": 1, "c": 3}, {"r": 0, "c": 3}], "target": 3, "op": "+"}, {"cells": [{"r": 0, "c": 2}, {"r": 1, "c": 2}], "target": 8, "op": "+"}, {"cells": [{"r": 0, "c": 1}, {"r": 1, "c": 1}], "target": 7, "op": "+"}, {"cells": [{"r": 2, "c": 2}, {"r": 3, "c": 2}], "target": 3, "op": "+"}, {"cells": [{"r": 4, "c": 2}], "target": 4, "op": "="}, {"cells": [{"r": 0, "c": 0}], "target": 1, "op": "="}], "solution": [[1, 5, 3, 2, 4], [4, 2, 5, 1, 3], [5, 4, 1, 3, 2], [3, 1, 2, 4, 5], [2, 3, 4, 5, 1]]}, {"id": "e-0-1747", "size": 5, "cages": [{"cells": [{"r": 4, "c": 2}], "target": 2, "op": "="}, {"cells": [{"r": 2, "c": 2}, {"r": 3, "c": 2}], "target": 7, "op": "+"}, {"cells": [{"r": 0, "c": 1}, {"r": 0, "c": 2}], "target": 5, "op": "+"}, {"cells": [{"r": 3, "c": 4}, {"r": 3, "c": 3}], "target": 9, "op": "+"}, {"cells": [{"r": 0, "c": 0}, {"r": 1, "c": 0}], "target": 8, "op": "+"}, {"cells": [{"r": 2, "c": 4}, {"r": 2, "c": 3}], "target": 5, "op": "+"}, {"cells": [{"r": 4, "c": 1}, {"r": 4, "c": 0}], "target": 7, "op": "+"}, {"cells": [{"r": 0, "c": 3}, {"r": 1, "c": 3}], "target": 7, "op": "+"}, {"cells": [{"r": 3, "c": 0}, {"r": 2, "c": 0}], "target": 3, "op": "+"}, {"cells": [{"r": 0, "c": 4}, {"r": 1, "c": 4}], "target": 3, "op": "+"}, {"cells": [{"r": 4, "c": 4}, {"r": 4, "c": 3}], "target": 6, "op": "+"}, {"cells": [{"r": 1, "c": 2}, {"r": 1, "c": 1}], "target": 7, "op": "+"}, {"cells": [{"r": 3, "c": 1}, {"r": 2, "c": 1}], "target": 6, "op": "+"}], "solution": [[5, 4, 1, 3, 2], [3, 2, 5, 4, 1], [1, 5, 4, 2, 3], [2, 1, 3, 5, 4], [4, 3, 2, 1, 5]]}, {"id": "e-0-5702", "size": 5, "cages": [{"cells": [{"r": 2, "c": 2}], "target": 1, "op": "="}, {"cells": [{"r": 0, "c": 2}, {"r": 1, "c": 2}], "target": 9, "op": "+"}, {"cells": [{"r": 4, "c": 0}, {"r": 4, "c": 1}], "target": 5, "op": "+"}, {"cells": [{"r": 3, "c": 2}, {"r": 3, "c": 1}], "target": 8, "op": "+"}, {"cells": [{"r": 0, "c": 4}, {"r": 0, "c": 3}], "target": 3, "op": "+"}, {"cells": [{"r": 1, "c": 3}, {"r": 2, "c": 3}], "target": 9, "op": "+"}, {"cells": [{"r": 4, "c": 3}, {"r": 3, "c": 3}], "target": 4, "op": "+"}, {"cells": [{"r": 0, "c": 1}, {"r": 1, "c": 1}], "target": 6, "op": "+"}, {"cells": [{"r": 1, "c": 4}, {"r": 2, "c": 4}], "target": 5, "op": "+"}, {"cells": [{"r": 4, "c": 4}, {"r": 3, "c": 4}], "target": 9, "op": "+"}, {"cells": [{"r": 0, "c": 0}, {"r": 1, "c": 0}], "target": 4, "op": "+"}, {"cells": [{"r": 2, "c": 0}, {"r": 3, "c": 0}], "target": 7, "op": "+"}, {"cells": [{"r": 2, "c": 1}], "target": 3, "op": "="}, {"cells": [{"r": 4, "c": 2}], "target": 2, "op": "="}], "solution": [[3, 4, 5, 2, 1], [1, 2, 4, 5, 3], [5, 3, 1, 4, 2], [2, 5, 3, 1, 4], [4, 1, 2, 3, 5]]}, {"id": "e-1-4497", "size": 5, "cages": [{"cells": [{"r": 4, "c": 4}], "target": 4, "op": "="}, {"cells": [{"r": 2, "c": 4}, {"r": 2, "c": 3}], "target": 4, "op": "+"}, {"cells": [{"r": 1, "c": 2}, {"r": 2, "c": 2}], "target": 7, "op": "+"}, {"cells": [{"r": 2, "c": 1}, {"r": 2, "c": 0}], "target": 7, "op": "+"}, {"cells": [{"r": 4, "c": 3}, {"r": 4, "c": 2}], "target": 5, "op": "+"}, {"cells": [{"r": 0, "c": 3}, {"r": 1, "c": 3}], "target": 7, "op": "+"}, {"cells": [{"r": 3, "c": 4}, {"r": 3, "c": 3}], "target": 9, "op": "+"}, {"cells": [{"r": 0, "c": 4}, {"r": 1, "c": 4}], "target": 3, "op": "+"}, {"cells": [{"r": 3, "c": 2}, {"r": 3, "c": 1}], "target": 4, "op": "+"}, {"cells": [{"r": 4, "c": 1}, {"r": 4, "c": 0}], "target": 6, "op": "+"}, {"cells": [{"r": 1, "c": 0}, {"r": 0, "c": 0}], "target": 7, "op": "+"}, {"cells": [{"r": 0, "c": 1}, {"r": 1, "c": 1}], "target": 5, "op": "+"}, {"cells": [{"r": 0, "c": 2}], "target": 5, "op": "="}, {"cells": [{"r": 3, "c": 0}], "target": 2, "op": "="}], "solution": [[3, 4, 5, 2, 1], [4, 1, 3, 5, 2], [5, 2, 4, 1, 3], [2, 3, 1, 4, 5], [1, 5, 2, 3, 4]]}, {"id": "e-0-8045", "size": 5, "cages": [{"cells": [{"r": 4, "c": 1}], "target": 4, "op": "="}, {"cells": [{"r": 3, "c": 2}, {"r": 3, "c": 1}], "target": 4, "op": "+"}, {"cells": [{"r": 0, "c": 4}, {"r": 1, "c": 4}], "target": 5, "op": "+"}, {"cells": [{"r": 4, "c": 4}, {"r": 3, "c": 4}], "target": 6, "op": "+"}, {"cells": [{"r": 4, "c": 2}, {"r": 4, "c": 3}], "target": 7, "op": "+"}, {"cells": [{"r": 0, "c": 0}, {"r": 0, "c": 1}], "target": 9, "op": "+"}, {"cells": [{"r": 2, "c": 3}, {"r": 1, "c": 3}], "target": 5, "op": "+"}, {"cells": [{"r": 3, "c": 3}], "target": 4, "op": "="}, {"cells": [{"r": 1, "c": 1}, {"r": 1, "c": 0}], "target": 6, "op": "+"}, {"cells": [{"r": 2, "c": 4}], "target": 4, "op": "="}, {"cells": [{"r": 0, "c": 3}, {"r": 0, "c": 2}], "target": 4, "op": "+"}, {"cells": [{"r": 1, "c": 2}, {"r": 2, "c": 2}], "target": 9, "op": "+"}, {"cells": [{"r": 4, "c": 0}, {"r": 3, "c": 0}], "target": 5, "op": "+"}, {"cells": [{"r": 2, "c": 0}, {"r": 2, "c": 1}], "target": 3, "op": "+"}], "solution": [[4, 5, 3, 1, 2], [5, 1, 4, 2, 3], [1, 2, 5, 3, 4], [2, 3, 1, 4, 5], [3, 4, 2, 5, 1]]}, {"id": "e-0-7094", "size": 5, "cages": [{"cells": [{"r": 1, "c": 0}], "target": 5, "op": "="}, {"cells": [{"r": 0, "c": 4}, {"r": 0, "c": 3}], "target": 9, "op": "+"}, {"cells": [{"r": 2, "c": 0}, {"r": 2, "c": 1}], "target": 5, "op": "+"}, {"cells": [{"r": 2, "c": 3}, {"r": 2, "c": 4}], "target": 8, "op": "+"}, {"cells": [{"r": 4, "c": 1}, {"r": 4, "c": 2}], "target": 8, "op": "+"}, {"cells": [{"r": 3, "c": 2}, {"r": 3, "c": 3}], "target": 6, "op": "+"}, {"cells": [{"r": 1, "c": 4}, {"r": 1, "c": 3}], "target": 3, "op": "+"}, {"cells": [{"r": 4, "c": 3}, {"r": 4, "c": 4}], "target": 6, "op": "+"}, {"cells": [{"r": 1, "c": 1}, {"r": 1, "c": 2}], "target": 7, "op": "+"}, {"cells": [{"r": 3, "c": 0}, {"r": 4, "c": 0}], "target": 3, "op": "+"}, {"cells": [{"r": 3, "c": 4}], "target": 3, "op": "="}, {"cells": [{"r": 2, "c": 2}], "target": 2, "op": "="}, {"cells": [{"r": 0, "c": 2}, {"r": 0, "c": 1}], "target": 3, "op": "+"}, {"cells": [{"r": 3, "c": 1}], "target": 4, "op": "="}, {"cells": [{"r": 0, "c": 0}], "target": 3, "op": "="}], "solution": [[3, 2, 1, 5, 4], [5, 3, 4, 2, 1], [4, 1, 2, 3, 5], [2, 4, 5, 1, 3], [1, 5, 3, 4, 2]]}, {"id": "e-1-9174", "size": 5, "cages": [{"cells": [{"r": 1, "c": 1}], "target": 4, "op": "="}, {"cells": [{"r": 1, "c": 3}, {"r": 1, "c": 2}], "target": 8, "op": "+"}, {"cells": [{"r": 4, "c": 1}, {"r": 3, "c": 1}], "target": 8, "op": "+"}, {"cells": [{"r": 1, "c": 4}, {"r": 2, "c": 4}], "target": 3, "op": "+"}, {"cells": [{"r": 4, "c": 2}, {"r": 3, "c": 2}], "target": 6, "op": "+"}, {"cells": [{"r": 0, "c": 0}, {"r": 0, "c": 1}], "target": 4, "op": "+"}, {"cells": [{"r": 4, "c": 4}, {"r": 3, "c": 4}], "target": 7, "op": "+"}, {"cells": [{"r": 1, "c": 0}, {"r": 2, "c": 0}], "target": 6, "op": "+"}, {"cells": [{"r": 0, "c": 4}, {"r": 0, "c": 3}], "target": 9, "op": "+"}, {"cells": [{"r": 3, "c": 0}, {"r": 4, "c": 0}], "target": 6, "op": "+"}, {"cells": [{"r": 2, "c": 1}, {"r": 2, "c": 2}], "target": 6, "op": "+"}, {"cells": [{"r": 2, "c": 3}, {"r": 3, "c": 3}], "target": 5, "op": "+"}, {"cells": [{"r": 0, "c": 2}], "target": 2, "op": "="}, {"cells": [{"r": 4, "c": 3}], "target": 1, "op": "="}], "solution": [[3, 1, 2, 4, 5], [1, 4, 3, 5, 2], [5, 2, 4, 3, 1], [4, 5, 1, 2, 3], [2, 3, 5, 1, 4]]}, {"id": "e-0-3018", "size": 5, "cages": [{"cells": [{"r": 1, "c": 3}], "target": 5, "op": "="}, {"cells": [{"r": 1, "c": 4}, {"r": 0, "c": 4}], "target": 5, "op": "+"}, {"cells": [{"r": 0, "c": 0}, {"r": 1, "c": 0}], "target": 8, "op": "+"}, {"cells": [{"r": 3, "c": 0}, {"r": 4, "c": 0}], "target": 3, "op": "+"}, {"cells": [{"r": 1, "c": 2}, {"r": 2, "c": 2}], "target": 7, "op": "+"}, {"cells": [{"r": 0, "c": 1}, {"r": 1, "c": 1}], "target": 3, "op": "+"}, {"cells": [{"r": 3, "c": 4}, {"r": 3, "c": 3}], "target": 8, "op": "+"}, {"cells": [{"r": 3, "c": 1}, {"r": 2, "c": 1}], "target": 9, "op": "+"}, {"cells": [{"r": 2, "c": 4}, {"r": 2, "c": 3}], "target": 3, "op": "+"}, {"cells": [{"r": 4, "c": 3}, {"r": 4, "c": 4}], "target": 5, "op": "+"}, {"cells": [{"r": 0, "c": 2}, {"r": 0, "c": 3}], "target": 5, "op": "+"}, {"cells": [{"r": 2, "c": 0}], "target": 4, "op": "="}, {"cells": [{"r": 4, "c": 2}, {"r": 4, "c": 1}], "target": 8, "op": "+"}, {"cells": [{"r": 3, "c": 2}], "target": 2, "op": "="}], "solution": [[5, 2, 1, 4, 3], [3, 1, 4, 5, 2], [4, 5, 3, 2, 1], [1, 4, 2, 3, 5], [2, 3, 5, 1, 4]]}, {"id": "e-1-5495", "size": 5, "cages": [{"cells": [{"r": 0, "c": 2}], "target": 1, "op": "="}, {"cells": [{"r": 4, "c": 2}, {"r": 4, "c": 1}], "target": 9, "op": "+"}, {"cells": [{"r": 1, "c": 0}, {"r": 1, "c": 1}], "target": 6, "op": "+"}, {"cells": [{"r": 3, "c": 4}, {"r": 2, "c": 4}], "target": 6, "op": "+"}, {"cells": [{"r": 2, "c": 3}, {"r": 1, "c": 3}], "target": 6, "op": "+"}, {"cells": [{"r": 3, "c": 2}, {"r": 3, "c": 3}], "target": 9, "op": "+"}, {"cells": [{"r": 2, "c": 2}, {"r": 2, "c": 1}], "target": 5, "op": "+"}, {"cells": [{"r": 1, "c": 4}, {"r": 0, "c": 4}], "target": 6, "op": "+"}, {"cells": [{"r": 4, "c": 0}, {"r": 3, "c": 0}], "target": 5, "op": "+"}, {"cells": [{"r": 4, "c": 4}, {"r": 4, "c": 3}], "target": 4, "op": "+"}, {"cells": [{"r": 0, "c": 3}], "target": 3, "op": "="}, {"cells": [{"r": 0, "c": 1}, {"r": 0, "c": 0}], "target": 9, "op": "+"}, {"cells": [{"r": 2, "c": 0}], "target": 1, "op": "="}, {"cells": [{"r": 3, "c": 1}], "target": 2, "op": "="}, {"cells": [{"r": 1, "c": 2}], "target": 3, "op": "="}], "solution": [[4, 5, 1, 3, 2], [5, 1, 3, 2, 4], [1, 3, 2, 4, 5], [3, 2, 4, 5, 1], [2, 4, 5, 1, 3]]}, {"id": "e-0-8698", "size": 5, "cages": [{"cells": [{"r": 4, "c": 0}], "target": 1, "op": "="}, {"cells": [{"r": 2, "c": 4}, {"r": 3, "c": 4}], "target": 5, "op": "+"}, {"cells": [{"r": 1, "c": 1}, {"r": 1, "c": 0}], "target": 8, "op": "+"}, {"cells": [{"r": 0, "c": 0}, {"r": 0, "c": 1}], "target": 7, "op": "+"}, {"cells": [{"r": 4, "c": 4}, {"r": 4, "c": 3}], "target": 7, "op": "+"}, {"cells": [{"r": 1, "c": 2}, {"r": 1, "c": 3}], "target": 6, "op": "+"}, {"cells": [{"r": 4, "c": 1}, {"r": 4, "c": 2}], "target": 7, "op": "+"}, {"cells": [{"r": 3, "c": 3}, {"r": 3, "c": 2}], "target": 9, "op": "+"}, {"cells": [{"r": 0, "c": 2}, {"r": 0, "c": 3}], "target": 4, "op": "+"}, {"cells": [{"r": 1, "c": 4}, {"r": 0, "c": 4}], "target": 5, "op": "+"}, {"cells": [{"r": 2, "c": 3}, {"r": 2, "c": 2}], "target": 6, "op": "+"}, {"cells": [{"r": 2, "c": 0}, {"r": 3, "c": 0}], "target": 6, "op": "+"}, {"cells": [{"r": 3, "c": 1}, {"r": 2, "c": 1}], "target": 4, "op": "+"}], "solution": [[5, 2, 1, 3, 4], [3, 5, 2, 4, 1], [4, 3, 5, 1, 2], [2, 1, 4, 5, 3], [1, 4, 3, 2, 5]]}, {"id": "e-1-7449", "size": 5, "cages": [{"cells": [{"r": 3, "c": 3}], "target": 3, "op": "="}, {"cells": [{"r": 4, "c": 3}, {"r": 4, "c": 2}], "target": 4, "op": "+"}, {"cells": [{"r": 0, "c": 0}, {"r": 1, "c": 0}], "target": 7, "op": "+"}, {"cells": [{"r": 4, "c": 0}, {"r": 3, "c": 0}], "target": 7, "op": "+"}, {"cells": [{"r": 4, "c": 4}, {"r": 3, "c": 4}], "target": 6, "op": "+"}, {"cells": [{"r": 4, "c": 1}, {"r": 3, "c": 1}], "target": 6, "op": "+"}, {"cells": [{"r": 2, "c": 4}, {"r": 2, "c": 3}], "target": 9, "op": "+"}, {"cells": [{"r": 0, "c": 1}, {"r": 0, "c": 2}], "target": 3, "op": "+"}, {"cells": [{"r": 1, "c": 4}, {"r": 1, "c": 3}], "target": 3, "op": "+"}, {"cells": [{"r": 3, "c": 2}, {"r": 2, "c": 2}], "target": 6, "op": "+"}, {"cells": [{"r": 0, "c": 4}, {"r": 0, "c": 3}], "target": 8, "op": "+"}, {"cells": [{"r": 2, "c": 0}, {"r": 2, "c": 1}], "target": 4, "op": "+"}, {"cells": [{"r": 1, "c": 1}, {"r": 1, "c": 2}], "target": 9, "op": "+"}], "solution": [[4, 2, 1, 5, 3], [3, 4, 5, 2, 1], [1, 3, 2, 4, 5], [5, 1, 4, 3, 2], [2, 5, 3, 1, 4]]}, {"id": "e-2-8875", "size": 5, "cages": [{"cells": [{"r": 4, "c": 4}], "target": 2, "op": "="}, {"cells": [{"r": 3, "c": 0}, {"r": 3, "c": 1}], "target": 3, "op": "+"}, {"cells": [{"r": 0, "c": 4}, {"r": 0, "c": 3}], "target": 9, "op": "+"}, {"cells": [{"r": 0, "c": 0}, {"r": 1, "c": 0}], "target": 7, "op": "+"}, {"cells": [{"r": 1, "c": 3}, {"r": 1, "c": 2}], "target": 6, "op": "+"}, {"cells": [{"r": 4, "c": 1}, {"r": 4, "c": 0}], "target": 7, "op": "+"}, {"cells": [{"r": 3, "c": 2}, {"r": 2, "c": 2}], "target": 7, "op": "+"}, {"cells": [{"r": 1, "c": 4}, {"r": 2, "c": 4}], "target": 4, "op": "+"}, {"cells": [{"r": 1, "c": 1}, {"r": 0, "c": 1}], "target": 4, "op": "+"}, {"cells": [{"r": 4, "c": 2}, {"r": 4, "c": 3}], "target": 6, "op": "+"}, {"cells": [{"r": 3, "c": 4}, {"r": 3, "c": 3}], "target": 8, "op": "+"}, {"cells": [{"r": 2, "c": 1}, {"r": 2, "c": 0}], "target": 9, "op": "+"}, {"cells": [{"r": 2, "c": 3}], "target": 2, "op": "="}, {"cells": [{"r": 0, "c": 2}], "target": 1, "op": "="}], "solution": [[2, 3, 1, 5, 4], [5, 1, 2, 4, 3], [4, 5, 3, 2, 1], [1, 2, 4, 3, 5], [3, 4, 5, 1, 2]]}, {"id": "e-0-6386", "size": 5, "cages": [{"cells": [{"r": 4, "c": 1}], "target": 1, "op": "="}, {"cells": [{"r": 1, "c": 4}, {"r": 2, "c": 4}], "target": 5, "op": "+"}, {"cells": [{"r": 1, "c": 1}, {"r": 2, "c": 1}], "target": 7, "op": "+"}, {"cells": [{"r": 0, "c": 4}, {"r": 0, "c": 3}], "target": 3, "op": "+"}, {"cells": [{"r": 4, "c": 2}, {"r": 4, "c": 3}], "target": 6, "op": "+"}, {"cells": [{"r": 1, "c": 0}, {"r": 2, "c": 0}], "target": 7, "op": "+"}, {"cells": [{"r": 4, "c": 0}, {"r": 3, "c": 0}], "target": 4, "op": "+"}, {"cells": [{"r": 3, "c": 4}, {"r": 4, "c": 4}], "target": 9, "op": "+"}, {"cells": [{"r": 3, "c": 3}, {"r": 3, "c": 2}], "target": 8, "op": "+"}, {"cells": [{"r": 1, "c": 2}, {"r": 0, "c": 2}], "target": 7, "op": "+"}, {"cells": [{"r": 2, "c": 2}, {"r": 2, "c": 3}], "target": 6, "op": "+"}, {"cells": [{"r": 1, "c": 3}], "target": 1, "op": "="}, {"cells": [{"r": 0, "c": 0}, {"r": 0, "c": 1}], "target": 9, "op": "+"}, {"cells": [{"r": 3, "c": 1}], "target": 2, "op": "="}], "solution": [[4, 5, 3, 2, 1], [5, 3, 4, 1, 2], [2, 4, 1, 5, 3], [1, 2, 5, 3, 4], [3, 1, 2, 4, 5]]}, {"id": "e-0-6407", "size": 5, "cages": [{"cells": [{"r": 3, "c": 0}], "target": 1, "op": "="}, {"cells": [{"r": 4, "c": 1}, {"r": 4, "c": 0}], "target": 9, "op": "+"}, {"cells": [{"r": 3, "c": 1}, {"r": 3, "c": 2}], "target": 6, "op": "+"}, {"cells": [{"r": 2, "c": 0}, {"r": 1, "c": 0}], "target": 7, "op": "+"}, {"cells": [{"r": 1, "c": 1}, {"r": 1, "c": 2}], "target": 5, "op": "+"}, {"cells": [{"r": 4, "c": 3}, {"r": 4, "c": 2}], "target": 5, "op": "+"}, {"cells": [{"r": 2, "c": 3}, {"r": 2, "c": 2}], "target": 3, "op": "+"}, {"cells": [{"r": 0, "c": 4}, {"r": 0, "c": 3}], "target": 6, "op": "+"}, {"cells": [{"r": 0, "c": 2}, {"r": 0, "c": 1}], "target": 6, "op": "+"}, {"cells": [{"r": 2, "c": 1}], "target": 3, "op": "="}, {"cells": [{"r": 0, "c": 0}], "target": 3, "op": "="}, {"cells": [{"r": 3, "c": 3}, {"r": 3, "c": 4}], "target": 8, "op": "+"}, {"cells": [{"r": 2, "c": 4}, {"r": 1, "c": 4}], "target": 7, "op": "+"}, {"cells": [{"r": 1, "c": 3}], "target": 5, "op": "="}, {"cells": [{"r": 4, "c": 4}], "target": 1, "op": "="}], "solution": [[3, 1, 5, 4, 2], [2, 4, 1, 5, 3], [5, 3, 2, 1, 4], [1, 2, 4, 3, 5], [4, 5, 3, 2, 1]]}, {"id": "e-2-1244", "size": 5, "cages": [{"cells": [{"r": 1, "c": 1}], "target": 5, "op": "="}, {"cells": [{"r": 2, "c": 3}, {"r": 2, "c": 2}], "target": 6, "op": "+"}, {"cells": [{"r": 0, "c": 3}, {"r": 1, "c": 3}], "target": 5, "op": "+"}, {"cells": [{"r": 2, "c": 1}, {"r": 3, "c": 1}], "target": 6, "op": "+"}, {"cells": [{"r": 2, "c": 0}, {"r": 1, "c": 0}], "target": 7, "op": "+"}, {"cells": [{"r": 3, "c": 2}, {"r": 4, "c": 2}], "target": 5, "op": "+"}, {"cells": [{"r": 4, "c": 0}, {"r": 3, "c": 0}], "target": 3, "op": "+"}, {"cells": [{"r": 0, "c": 1}, {"r": 0, "c": 2}], "target": 5, "op": "+"}, {"cells": [{"r": 1, "c": 2}], "target": 1, "op": "="}, {"cells": [{"r": 3, "c": 4}, {"r": 4, "c": 4}], "target": 6, "op": "+"}, {"cells": [{"r": 4, "c": 3}, {"r": 3, "c": 3}], "target": 9, "op": "+"}, {"cells": [{"r": 0, "c": 4}, {"r": 1, "c": 4}], "target": 6, "op": "+"}, {"cells": [{"r": 0, "c": 0}], "target": 5, "op": "="}, {"cells": [{"r": 2, "c": 4}], "target": 3, "op": "="}, {"cells": [{"r": 4, "c": 1}], "target": 3, "op": "="}], "solution": [[5, 1, 4, 3, 2], [3, 5, 1, 2, 4], [4, 2, 5, 1, 3], [2, 4, 3, 5, 1], [1, 3, 2, 4, 5]]}, {"id": "e-1-3179", "size": 5, "cages": [{"cells": [{"r": 0, "c": 0}], "target": 3, "op": "="}, {"cells": [{"r": 3, "c": 1}, {"r": 3, "c": 2}], "target": 4, "op": "+"}, {"cells": [{"r": 0, "c": 1}, {"r": 1, "c": 1}], "target": 8, "op": "+"}, {"cells": [{"r": 0, "c": 4}, {"r": 0, "c": 3}], "target": 5, "op": "+"}, {"cells": [{"r": 2, "c": 0}, {"r": 3, "c": 0}], "target": 9, "op": "+"}, {"cells": [{"r": 1, "c": 4}, {"r": 2, "c": 4}], "target": 4, "op": "+"}, {"cells": [{"r": 4, "c": 3}, {"r": 3, "c": 3}], "target": 5, "op": "+"}, {"cells": [{"r": 3, "c": 4}, {"r": 4, "c": 4}], "target": 7, "op": "+"}, {"cells": [{"r": 4, "c": 1}, {"r": 4, "c": 0}], "target": 5, "op": "+"}, {"cells": [{"r": 2, "c": 1}, {"r": 2, "c": 2}], "target": 3, "op": "+"}, {"cells": [{"r": 0, "c": 2}, {"r": 1, "c": 2}], "target": 6, "op": "+"}, {"cells": [{"r": 4, "c": 2}], "target": 5, "op": "="}, {"cells": [{"r": 2, "c": 3}, {"r": 1, "c": 3}], "target": 9, "op": "+"}, {"cells": [{"r": 1, "c": 0}], "target": 2, "op": "="}], "solution": [[3, 5, 2, 1, 4], [2, 3, 4, 5, 1], [5, 2, 1, 4, 3], [4, 1, 3, 2, 5], [1, 4, 5, 3, 2]]}, {"id": "e-0-9669", "size": 5, "cages": [{"cells": [{"r": 1, "c": 2}], "target": 1, "op": "="}, {"cells": [{"r": 3, "c": 1}, {"r": 3, "c": 2}], "target": 7, "op": "+"}, {"cells": [{"r": 2, "c": 1}, {"r": 2, "c": 2}], "target": 8, "op": "+"}, {"cells": [{"r": 1, "c": 1}, {"r": 1, "c": 0}], "target": 7, "op": "+"}, {"cells": [{"r": 4, "c": 2}, {"r": 4, "c": 3}], "target": 7, "op": "+"}, {"cells": [{"r": 0, "c": 0}, {"r": 0, "c": 1}], "target": 8, "op": "+"}, {"cells": [{"r": 3, "c": 0}, {"r": 2, "c": 0}], "target": 5, "op": "+"}, {"cells": [{"r": 0, "c": 2}, {"r": 0, "c": 3}], "target": 6, "op": "+"}, {"cells": [{"r": 3, "c": 3}, {"r": 3, "c": 4}], "target": 4, "op": "+"}, {"cells": [{"r": 1, "c": 3}, {"r": 1, "c": 4}], "target": 7, "op": "+"}, {"cells": [{"r": 4, "c": 0}, {"r": 4, "c": 1}], "target": 3, "op": "+"}, {"cells": [{"r": 2, "c": 4}, {"r": 2, "c": 3}], "target": 6, "op": "+"}, {"cells": [{"r": 0, "c": 4}], "target": 1, "op": "="}, {"cells": [{"r": 4, "c": 4}], "target": 5, "op": "="}], "solution": [[5, 3, 2, 4, 1], [3, 4, 1, 5, 2], [1, 5, 3, 2, 4], [4, 2, 5, 1, 3], [2, 1, 4, 3, 5]]}, {"id": "e-0-5666", "size": 5, "cages": [{"cells": [{"r": 1, "c": 3}], "target": 2, "op": "="}, {"cells": [{"r": 0, "c": 2}, {"r": 0, "c": 3}], "target": 4, "op": "+"}, {"cells": [{"r": 2, "c": 3}, {"r": 2, "c": 2}], "target": 6, "op": "+"}, {"cells": [{"r": 2, "c": 0}, {"r": 1, "c": 0}], "target": 6, "op": "+"}, {"cells": [{"r": 2, "c": 4}, {"r": 1, "c": 4}], "target": 4, "op": "+"}, {"cells": [{"r": 4, "c": 4}, {"r": 4, "c": 3}], "target": 7, "op": "+"}, {"cells": [{"r": 3, "c": 0}, {"r": 3, "c": 1}], "target": 3, "op": "+"}, {"cells": [{"r": 0, "c": 1}, {"r": 0, "c": 0}], "target": 6, "op": "+"}, {"cells": [{"r": 4, "c": 0}, {"r": 4, "c": 1}], "target": 7, "op": "+"}, {"cells": [{"r": 1, "c": 2}, {"r": 1, "c": 1}], "target": 7, "op": "+"}, {"cells": [{"r": 3, "c": 4}, {"r": 3, "c": 3}], "target": 7, "op": "+"}, {"cells": [{"r": 4, "c": 2}, {"r": 3, "c": 2}], "target": 6, "op": "+"}, {"cells": [{"r": 0, "c": 4}], "target": 5, "op": "="}, {"cells": [{"r": 2, "c": 1}], "target": 5, "op": "="}], "solution": [[4, 2, 3, 1, 5], [5, 3, 4, 2, 1], [1, 5, 2, 4, 3], [2, 1, 5, 3, 4], [3, 4, 1, 5, 2]]}]